<?xml version="1.0" encoding="utf-8"?>
<unigal-script>
  <head>
    <src_engine>
      Librian
    </src_engine>
  </head>
  <body>
    <resource type="layer">
      <layer_ID>
        01
      </layer_ID>
      <layer_name>
        Librian_background
      </layer_name>
      <layer_opacity>
        255
      </layer_opacity>
      <layer_transparent>
        100
      </layer_transparent>
    </resource>
    <resource type="layer">
      <layer_ID>
        02
      </layer_ID>
      <layer_name>
        Librian_tachie
      </layer_name>
      <layer_opacity>
        255
      </layer_opacity>
      <layer_transparent>
        100
      </layer_transparent>
    </resource>
    <resource type="index">
      <layerlist>
        <layer_ID>02</layer_ID>
        <layer_ID>01</layer_ID>
      </layerlist>
    </resource>
    <!-- Librian暂无需要预处理的内容，因此直接定义句数就可以 -->
    <!-- 不过只要涉及到图像和音频，就有必要提前预定义layer和channel -->
    <struct>
      <count>
        1
      </count>
    </struct>
    <code>
      <resource type="image">
        <image>
          <img_ID>
            001
          </img_ID>
          <layer_ID>
            02
          </layer_ID>
          <file>
            (['裸體']@{'潘大爺.psd'})
          </file>
        </image>
        <tachie>
          <cloth>
            裸體
          </cloth>
        </tachie>
      </resource>
    </code>
    <struct>
      <count>
        2
      </count>
    </struct>
    <code>
      <resource type="image">
        <image>
          <img_ID>
            002
          </img_ID>
          <layer_ID>
            02
          </layer_ID>
          <file>
            (['默認表情']@{'潘大爺.psd'})
          </file>
        </image>
        <tachie>
          <expression>
            默認表情
          </expression>
        </tachie>
      </resource>
    </code>
    <action>
      <showimage>
        <!--意思意思-->
      </showimage>
    </action>
    <!--暂定为先画图，后写字-->
    <text>
      <character>
        <name>
          潘大爺
        </name>
      </character>
      <content>
        <part>
          我看看……
        </part>
      </content>
    </text>
    <struct>
      <count>
        3
      </count>
    </struct>
    <code>
      <resource type="image">
        <image>
          <img_ID>
            003
          </img_ID>
          <layer_ID>
            02
          </layer_ID>
          <file>
            (['大笑']@{'潘大爺.psd'})
          </file>
        </image>
        <tachie>
          <expression>
            大笑
          </expression>
        </tachie>
      </resource>
    </code>
    <!--暂定为先画图，后写字-->
    <text>
      <character>
        <name>
          潘大爺
        </name>
      </character>
      <content>
        <part>
          哈哈哈，你是豬嗎？
        </part>
      </content>
    </text>
  </body>
</unigal-script>